pymbse/exec/__init__.py
pymbse/exec/celery.py
pymbse/exec/io.py
pymbse/exec/tools.py
pymbse_exec-0.0.4.dist-info/LICENSES/BSD-4-Clause.txt
pymbse_exec-0.0.4.dist-info/LICENSES/CC0-1.0.txt
pymbse_exec-0.0.4.dist-info/METADATA
pymbse_exec-0.0.4.dist-info/WHEEL
pymbse_exec-0.0.4.dist-info/RECORD
